.editorconfig
.gitignore
.gitlab-ci.yml
LICENSE
README.rst
publish.settings.sh
publish.sh
pyproject.toml
.idea/modules.xml
.idea/peek-field-app.iml
.idea/inspectionProfiles/Project_Default.xml
.idea/inspectionProfiles/profiles_settings.xml
dev-scripts/pf_app_open_in_xcode.sh
dev-scripts/pf_repackage_ipa.sh
dev-scripts/icons/DEV.png
dev-scripts/icons/OREG.png
dev-scripts/icons/TEST.png
peek_field_app/.browserslistrc
peek_field_app/.gitignore
peek_field_app/README.md
peek_field_app/__init__.py
peek_field_app/angular.json
peek_field_app/capacitor.config.ts
peek_field_app/ngsw-config.json
peek_field_app/package-lock.json
peek_field_app/package.json
peek_field_app/proxy.conf.json
peek_field_app/tsconfig.app.json
peek_field_app/tsconfig.json
peek_field_app/tsconfig.spec.json
peek_field_app/tsconfig.worker.json
peek_field_app.egg-info/PKG-INFO
peek_field_app.egg-info/SOURCES.txt
peek_field_app.egg-info/dependency_links.txt
peek_field_app.egg-info/requires.txt
peek_field_app.egg-info/top_level.txt
peek_field_app/android/.gitignore
peek_field_app/android/build.gradle
peek_field_app/android/capacitor.settings.gradle
peek_field_app/android/gradle.properties
peek_field_app/android/gradlew
peek_field_app/android/gradlew.bat
peek_field_app/android/settings.gradle
peek_field_app/android/variables.gradle
peek_field_app/android/app/.npmignore
peek_field_app/android/app/build.gradle
peek_field_app/android/app/capacitor.build.gradle
peek_field_app/android/app/proguard-rules.pro
peek_field_app/android/app/src/androidTest/java/com/getcapacitor/myapp/ExampleInstrumentedTest.java
peek_field_app/android/app/src/main/AndroidManifest.xml
peek_field_app/android/app/src/main/assets/capacitor.config.json
peek_field_app/android/app/src/main/assets/capacitor.plugins.json
peek_field_app/android/app/src/main/java/com/synerty/peek/MainActivity.java
peek_field_app/android/app/src/main/res/drawable/ic_launcher_background.xml
peek_field_app/android/app/src/main/res/drawable/splash.png
peek_field_app/android/app/src/main/res/drawable-land-hdpi/splash.png
peek_field_app/android/app/src/main/res/drawable-land-mdpi/splash.png
