Metadata-Version: 2.4
Name: peek-field-app
Version: 5.0.4
Summary: Peek Field UI App - the Angular Web build environment for Peek Field
Author-email: Synerty <contact@synerty.com>
Project-URL: Homepage, https://github.com/Synerty/peek-field-app
Keywords: Peek,Python,Platform,synerty
License-File: LICENSE
Requires-Dist: peek-plugin-base==5.0.4
Dynamic: license-file
